fretty_book/__init__.py
fretty_book/__main__.py
fretty_book/processor.py
fretty_book-0.1.dist-info/LICENSE
fretty_book-0.1.dist-info/METADATA
fretty_book-0.1.dist-info/WHEEL
fretty_book-0.1.dist-info/entry_points.txt
fretty_book-0.1.dist-info/top_level.txt
fretty_book-0.1.dist-info/RECORD
