Metadata-Version: 2.1
Name: fretty-book
Version: 0.1
Summary: fretty-book can replace inline fretty markup within documents with the generated images
Home-page: https://github.com/thomasvolk/fretty-book
Author: Thomas Volk
Author-email: info@thomasvolk.de
License: Apache
Platform: any
Classifier: Programming Language :: Python :: 3.9
Classifier: License :: OSI Approved :: Apache Software License
Classifier: Operating System :: OS Independent
Classifier: Topic :: Text Processing :: Markup
Requires-Python: >=3.9.0
License-File: LICENSE
Requires-Dist: fretty[png]
Requires-Dist: lxml
